{
  "generatedAt": "2026-07-22T20:20:12.344Z",
  "config": {
    "liabilityDurationYears": 10,
    "liabilityValueGBP": 100000000
  },
  "gilts": {
    "gilt10y": {
      "date": "2026-07-20",
      "latest": 5.0195,
      "changes": {
        "daily": 7.6,
        "weekly": 6.9,
        "monthly": 29.8,
        "ytd": 55.3
      },
      "label": "10-Year Gilt"
    },
    "gilt20y": {
      "date": "2026-07-20",
      "latest": 5.5119,
      "changes": {
        "daily": 7.8,
        "weekly": 7,
        "monthly": 28.6,
        "ytd": 50.9
      },
      "label": "20-Year Gilt"
    }
  },
  "liabilityImpact": {
    "daily": {
      "changeBp": 7.8,
      "liabilityChangePct": -0.78,
      "direction": "liabilities-down"
    },
    "weekly": {
      "changeBp": 7,
      "liabilityChangePct": -0.7,
      "direction": "liabilities-down"
    },
    "monthly": {
      "changeBp": 28.6,
      "liabilityChangePct": -2.86,
      "direction": "liabilities-down"
    },
    "ytd": {
      "changeBp": 50.9,
      "liabilityChangePct": -5.09,
      "direction": "liabilities-down"
    }
  },
  "snapshot": {
    "ftse100": {
      "value": 10716.97,
      "changePct": 1.91
    },
    "sp500": {
      "value": 7498.96,
      "changePct": -0.97
    },
    "gbpusd": {
      "value": 1.34,
      "changePct": -1.21
    },
    "us10y": {
      "value": 4.67,
      "dailyBp": 4
    },
    "us20y": {
      "value": 5.17,
      "dailyBp": 3
    },
    "gilt10y": {
      "value": 5.0195,
      "dailyBp": 7.6
    },
    "gilt20y": {
      "value": 5.5119,
      "dailyBp": 7.8
    }
  },
  "errors": []
}